hugo_jupyter/__fabfile.py
hugo_jupyter/__init__.py
hugo_jupyter/cli.py
hugo_jupyter/hugo_jupyter.py
hugo_jupyter-1.0.2.dist-info/DESCRIPTION.rst
hugo_jupyter-1.0.2.dist-info/METADATA
hugo_jupyter-1.0.2.dist-info/RECORD
hugo_jupyter-1.0.2.dist-info/WHEEL
hugo_jupyter-1.0.2.dist-info/entry_points.txt
hugo_jupyter-1.0.2.dist-info/metadata.json
hugo_jupyter-1.0.2.dist-info/top_level.txt
tests/__init__.py
tests/test_hugo_jupyter.py
